LICENSE
MANIFEST.in
README.md
setup.py
mkcloud/__init__.py
mkcloud/mqtt.py
mkcloud/robot.py
mkcloud.egg-info/PKG-INFO
mkcloud.egg-info/SOURCES.txt
mkcloud.egg-info/dependency_links.txt
mkcloud.egg-info/requires.txt
mkcloud.egg-info/top_level.txt