Metadata-Version: 2.1
Name: mkcloud
Version: 0.0.9
Summary: 通过童心制物云服务可以进行人工智能、聊天机器人、常用网络 api 获取等常用云服务。
Home-page: https://github.com/pypa/mkcloud
Author: makeblock
Author-email: developer@makeblock.com
License: MIT
Platform: all
Classifier: License :: OSI Approved :: MIT License
Classifier: Programming Language :: Python
Classifier: Programming Language :: Python :: 3
Classifier: Programming Language :: Python :: 3.6
Classifier: Programming Language :: Python :: Implementation :: CPython
Classifier: Programming Language :: Python :: Implementation :: PyPy
Requires-Python: >=3.6.0
